algomancy/__init__.py
algomancy-0.3.18.dist-info/licenses/LICENSE
algomancy-0.3.18.dist-info/WHEEL
algomancy-0.3.18.dist-info/entry_points.txt
algomancy-0.3.18.dist-info/METADATA
algomancy-0.3.18.dist-info/RECORD
