Metadata-Version: 2.4
Name: Algomancy
Version: 0.3.18
Summary: A dashboarding framework for visualizing performances of algorithms or simulations in various scenarios.
Keywords: visualization,algorithm,simulation,scenario
Author: Pepijn Wissing
Author-email: Pepijn Wissing <pepijn.wissing@cqm.nl>
License-File: LICENSE
Classifier: Development Status :: 4 - Beta
Classifier: Programming Language :: Python
Requires-Dist: algomancy-cli>=0.3.18
Requires-Dist: algomancy-content>=0.3.18
Requires-Dist: algomancy-data>=0.3.18
Requires-Dist: algomancy-gui>=0.3.18
Requires-Dist: algomancy-scenario>=0.3.18
Requires-Dist: algomancy-utils>=0.3.18
Requires-Dist: furo>=2025.12.19
Requires-Dist: myst-parser>=5.0.0
Requires-Dist: pydata-sphinx-theme>=0.16.1
Requires-Dist: sphinx>=9.1.0
Requires-Dist: sphinx-autobuild>=2025.8.25
Requires-Dist: sphinx-autodoc2>=0.5.0
Requires-Dist: sphinx-copybutton>=0.5.2
Requires-Dist: sphinx-design>=0.7.0
Requires-Dist: sphinx-rtd-theme>=3.1.0
Maintainer: Pepijn Wissing, Bart Post
Maintainer-email: Pepijn Wissing <pepijn.wissing@cqm.nl>, Bart Post <bart.post@cqm.nl>
Requires-Python: >=3.14
Project-URL: Documentation, https://algomancy.readthedocs.io/en/latest/
Project-URL: Repository, https://github.com/PepijnWissing/algomancy
